odoo/addons/account_move_tier_validation/README.rst
odoo/addons/account_move_tier_validation/__init__.py
odoo/addons/account_move_tier_validation/__manifest__.py
odoo/addons/account_move_tier_validation/i18n/account_move_tier_validation.pot
odoo/addons/account_move_tier_validation/i18n/ca.po
odoo/addons/account_move_tier_validation/i18n/de.po
odoo/addons/account_move_tier_validation/i18n/es.po
odoo/addons/account_move_tier_validation/i18n/es_PA.po
odoo/addons/account_move_tier_validation/i18n/fr.po
odoo/addons/account_move_tier_validation/i18n/hr.po
odoo/addons/account_move_tier_validation/i18n/it.po
odoo/addons/account_move_tier_validation/i18n/nl.po
odoo/addons/account_move_tier_validation/i18n/sv.po
odoo/addons/account_move_tier_validation/i18n/zh_CN.po
odoo/addons/account_move_tier_validation/models/__init__.py
odoo/addons/account_move_tier_validation/models/account_move.py
odoo/addons/account_move_tier_validation/models/tier_definition.py
odoo/addons/account_move_tier_validation/readme/CONFIGURE.md
odoo/addons/account_move_tier_validation/readme/CONTRIBUTORS.md
odoo/addons/account_move_tier_validation/readme/DESCRIPTION.md
odoo/addons/account_move_tier_validation/readme/INSTALL.md
odoo/addons/account_move_tier_validation/readme/USAGE.md
odoo/addons/account_move_tier_validation/static/description/icon.png
odoo/addons/account_move_tier_validation/static/description/index.html
odoo/addons/account_move_tier_validation/tests/__init__.py
odoo/addons/account_move_tier_validation/tests/test_tier_validation.py
odoo/addons/account_move_tier_validation/views/account_move_view.xml
odoo_addon_account_move_tier_validation-18.0.1.0.2.dist-info/METADATA
odoo_addon_account_move_tier_validation-18.0.1.0.2.dist-info/WHEEL
odoo_addon_account_move_tier_validation-18.0.1.0.2.dist-info/top_level.txt
odoo_addon_account_move_tier_validation-18.0.1.0.2.dist-info/RECORD
